pydatafaker/__init__.py
pydatafaker/business.py
pydatafaker/school.py
pydatafaker/utilities.py
pydatafaker-0.1.2.dist-info/LICENSE
pydatafaker-0.1.2.dist-info/WHEEL
pydatafaker-0.1.2.dist-info/METADATA
pydatafaker-0.1.2.dist-info/RECORD
