Metadata-Version: 2.1
Name: pydatafaker
Version: 0.1.2
Summary: A python package to create fake data with relationships between tables.
Home-page: https://github.com/SamEdwardes/pydatafaker
License: MIT
Keywords: python,fake,data,fake-data
Author: Sam Edwardes
Requires-Python: >=3.7,<4.0
Classifier: License :: OSI Approved :: MIT License
Classifier: Programming Language :: Python :: 3
Classifier: Programming Language :: Python :: 3.7
Classifier: Programming Language :: Python :: 3.8
Classifier: Programming Language :: Python :: 3.9
Requires-Dist: faker (>=4.1.2,<5.0.0)
Requires-Dist: pandas (>=1.1.1,<2.0.0)
Project-URL: Documentation, https://pydatafaker.readthedocs.io/en/latest/index.html
Project-URL: Repository, https://github.com/SamEdwardes/pydatafaker
